{
  "caseId": "CASE-2024-002",
  "metadata": {
    "title": "Roubo na Clínica",
    "description": "Roubo na madrugada de segunda-feira em clínica particular. Cofre arrombado, documentos confidenciais desapareceram. Porta trancada sem sinais de arrombamento. Apenas pessoas com acesso interno poderiam entrar na área restrita.",
    "startDateTime": "2024-02-05T08:00:00Z",
    "location": "Clínica Médica São Lucas, Bairro Jardins",
    "incidentDateTime": "2024-02-05T03:30:00Z",
    "victimInfo": {
      "name": "Clínica Médica São Lucas",
      "age": 0,
      "occupation": "Estabelecimento médico",
      "causeOfDeath": "Roubo de documentos confidenciais"
    },
    "briefing": "Na madrugada de segunda-feira, um roubo ocorreu em uma clínica particular. Um cofre foi arrombado e documentos confidenciais desapareceram. A porta da frente estava trancada sem sinais de arrombamento. Apenas pessoas com acesso interno poderiam entrar na área restrita onde o cofre se encontrava. Três pessoas estavam presentes no prédio nas horas anteriores ao crime.",
    "difficulty": 3,
    "estimatedDuration": "1-2 horas",
    "minRankRequired": "Cadet"
  },
  "evidences": [
    {
      "id": "EVD001",
      "name": "Relatório Inicial da Cena",
      "type": "document",
      "fileName": "relatorio_inicial_clinica.pdf",
      "category": "Document",
      "priority": "High",
      "description": "Relatório inicial da perícia na clínica após o roubo",
      "location": "evidence/",
      "isUnlocked": true,
      "requiresAnalysis": false,
      "dependsOn": [],
      "linkedSuspects": ["all"],
      "unlockConditions": {
        "immediate": true
      }
    },
    {
      "id": "EVD002",
      "name": "Fio de Cabelo Loiro",
      "type": "physical",
      "fileName": "fio_cabelo_loiro.jpg",
      "category": "Physical",
      "priority": "Critical",
      "description": "Fio de cabelo loiro encontrado no chão do consultório onde fica o cofre",
      "location": "evidence/",
      "isUnlocked": true,
      "requiresAnalysis": true,
      "dependsOn": [],
      "linkedSuspects": ["SUS001", "SUS002"],
      "analysisRequired": ["DNA"],
      "unlockConditions": {
        "immediate": true
      }
    },
    {
      "id": "EVD003",
      "name": "Imagem da Câmera de Segurança",
      "type": "image",
      "fileName": "camera_seguranca.jpg",
      "category": "Digital",
      "priority": "Critical",
      "description": "Imagem da câmera de segurança mostrando entrada da clínica",
      "location": "evidence/",
      "isUnlocked": true,
      "requiresAnalysis": true,
      "dependsOn": [],
      "linkedSuspects": ["SUS001"],
      "analysisRequired": ["DigitalForensics"],
      "unlockConditions": {
        "immediate": true
      }
    },
    {
      "id": "EVD004",
      "name": "Carta Manuscrita",
      "type": "document",
      "fileName": "carta_manuscrita.pdf",
      "category": "Document",
      "priority": "High",
      "description": "Carta manuscrita com conteúdo suspeito encontrada na gaveta da mesa",
      "location": "evidence/",
      "isUnlocked": false,
      "requiresAnalysis": true,
      "dependsOn": ["EVD001"],
      "linkedSuspects": ["SUS001"],
      "analysisRequired": ["HandwritingAnalysis"],
      "unlockConditions": {
        "timeDelay": 15,
        "triggerEvent": "evidenceExamined",
        "requiredEvidence": ["EVD001"]
      }
    },
    {
      "id": "EVD005",
      "name": "Bilhete Romântico Antigo",
      "type": "document",
      "fileName": "bilhete_romantico.txt",
      "category": "Document",
      "priority": "Low",
      "description": "Bilhete romântico antigo encontrado no lixo - evidência distrativa",
      "location": "evidence/",
      "isUnlocked": false,
      "requiresAnalysis": false,
      "dependsOn": ["EVD002"],
      "linkedSuspects": [],
      "unlockConditions": {
        "timeDelay": 10,
        "triggerEvent": "evidenceExamined",
        "requiredEvidence": ["EVD002"]
      }
    },
    {
      "id": "EVD006",
      "name": "Recibo de Farmácia",
      "type": "document",
      "fileName": "recibo_farmacia.jpg",
      "category": "Document",
      "priority": "Low",
      "description": "Recibo de farmácia encontrado no bolso do jaleco - evidência distrativa",
      "location": "evidence/",
      "isUnlocked": false,
      "requiresAnalysis": false,
      "dependsOn": ["EVD003"],
      "linkedSuspects": [],
      "unlockConditions": {
        "timeDelay": 5,
        "triggerEvent": "evidenceExamined",
        "requiredEvidence": ["EVD003"]
      }
    },
    {
      "id": "EVD007",
      "name": "Chave Estranha",
      "type": "physical",
      "fileName": "chave_estranha.jpg",
      "category": "Physical",
      "priority": "Low",
      "description": "Chave que não abre nada na clínica - evidência distrativa",
      "location": "evidence/",
      "isUnlocked": false,
      "requiresAnalysis": false,
      "dependsOn": ["EVD004"],
      "linkedSuspects": [],
      "unlockConditions": {
        "timeDelay": 8,
        "triggerEvent": "evidenceExamined",
        "requiredEvidence": ["EVD004"]
      }
    },
    {
      "id": "EVD008",
      "name": "Agenda Pessoal",
      "type": "document",
      "fileName": "agenda_rabiscos.pdf",
      "category": "Document",
      "priority": "Low",
      "description": "Agenda pessoal com rabiscos sem relação com o crime",
      "location": "evidence/",
      "isUnlocked": false,
      "requiresAnalysis": false,
      "dependsOn": ["EVD005"],
      "linkedSuspects": [],
      "unlockConditions": {
        "timeDelay": 12,
        "triggerEvent": "evidenceExamined",
        "requiredEvidence": ["EVD005"]
      }
    },
    {
      "id": "EVD009",
      "name": "Ficha de Paciente",
      "type": "document",
      "fileName": "ficha_paciente_irrelevante.pdf",
      "category": "Document",
      "priority": "Low",
      "description": "Ficha de paciente sem relação com o caso - evidência distrativa",
      "location": "evidence/",
      "isUnlocked": false,
      "requiresAnalysis": false,
      "dependsOn": ["EVD006"],
      "linkedSuspects": [],
      "unlockConditions": {
        "timeDelay": 7,
        "triggerEvent": "evidenceExamined",
        "requiredEvidence": ["EVD006"]
      }
    },
    {
      "id": "EVD010",
      "name": "Caderno com Anotações",
      "type": "document",
      "fileName": "caderno_anotacoes.pdf",
      "category": "Document",
      "priority": "Low",
      "description": "Caderno com anotações médicas sem relação com o crime",
      "location": "evidence/",
      "isUnlocked": false,
      "requiresAnalysis": false,
      "dependsOn": ["EVD007"],
      "linkedSuspects": [],
      "unlockConditions": {
        "timeDelay": 15,
        "triggerEvent": "evidenceExamined",
        "requiredEvidence": ["EVD007"]
      }
    }
  ],
  "suspects": [
    {
      "id": "SUS001",
      "name": "Joana Duarte",
      "alias": null,
      "age": 29,
      "occupation": "Enfermeira Chefe",
      "description": "Enfermeira chefe da clínica há 5 anos. Tem acesso total às instalações, incluindo a sala do cofre. Conhece todos os protocolos de segurança e rotinas da clínica.",
      "relationship": "Funcionária sênior com acesso total",
      "motive": "Problemas financeiros graves após divórcio. Foi flagrada alterando receitas médicas para venda ilegal de medicamentos controlados.",
      "alibi": "Afirma ter saído às 22:00 e ido direto para casa dormir",
      "alibiVerified": false,
      "behavior": "Nervosa, evita contato visual, gagueja ao falar sobre os horários",
      "backgroundInfo": "Divorciada há 6 meses, perdeu a guarda da filha, dívidas do cartão de crédito altas, cabelo loiro natural",
      "linkedEvidence": ["EVD001", "EVD002", "EVD003", "EVD004"],
      "comments": "Única pessoa além do médico-chefe com chave da sala do cofre",
      "isActualCulprit": true,
      "status": "PersonOfInterest",
      "unlockConditions": {
        "immediate": true
      }
    },
    {
      "id": "SUS002",
      "name": "Roberto Silva",
      "alias": "Dr. Beto",
      "age": 34,
      "occupation": "Médico Assistente",
      "description": "Médico jovem especialista em cardiologia. Trabalha na clínica há 2 anos. Tem acesso limitado, não possui chave da sala do cofre, mas conhece as rotinas.",
      "relationship": "Médico assistente com acesso limitado",
      "motive": "Descobriu esquema de superfaturamento de procedimentos e estava sendo pressionado a participar ou seria demitido",
      "alibi": "Estava no plantão do hospital público até 01:00, depois foi para casa",
      "alibiVerified": true,
      "behavior": "Cooperativo, mas demonstra nervosismo ao falar sobre pressões no trabalho",
      "backgroundInfo": "Médico recém-formado, ainda pagando residência, cabelo loiro descolorido, família tradicional de médicos",
      "linkedEvidence": ["EVD002", "EVD006"],
      "comments": "Não tem chave da sala do cofre, mas conhece os protocolos",
      "isActualCulprit": false,
      "status": "PersonOfInterest",
      "unlockConditions": {
        "immediate": true
      }
    },
    {
      "id": "SUS003",
      "name": "Carmen Rodriguez",
      "alias": null,
      "age": 45,
      "occupation": "Administradora",
      "description": "Administradora da clínica há 8 anos. Responsável pela parte financeira e administrativa. Tem acesso aos registros, mas não à sala do cofre.",
      "relationship": "Administradora sem acesso físico ao cofre",
      "motive": "Descontentamento com salário baixo e descoberta de que ganha menos que funcionários mais novos",
      "alibi": "Estava em casa com a família, assistindo filme até tarde",
      "alibiVerified": true,
      "behavior": "Controlada, profissional, mas demonstra ressentimento sutil com a gestão",
      "backgroundInfo": "Viúva, três filhos adolescentes, cabelo castanho escuro, trabalha há anos na clínica",
      "linkedEvidence": ["EVD001", "EVD008", "EVD009"],
      "comments": "Conhece todas as operações financeiras mas não tem acesso físico ao cofre",
      "isActualCulprit": false,
      "status": "PersonOfInterest",
      "unlockConditions": {
        "timeDelay": 10,
        "triggerEvent": "evidenceExamined",
        "requiredEvidence": ["EVD001"]
      }
    }
  ],
  "forensicAnalyses": [
    {
      "id": "DNA-EVD002",
      "evidenceId": "EVD002",
      "analysisType": "DNA",
      "responseTime": 90,
      "resultFile": "forensics/dna_cabelo_resultado.pdf",
      "description": "Análise de DNA do fio de cabelo loiro encontrado na cena"
    },
    {
      "id": "DIGITAL-EVD003",
      "evidenceId": "EVD003",
      "analysisType": "DigitalForensics",
      "responseTime": 60,
      "resultFile": "forensics/camera_analysis.pdf",
      "description": "Análise da imagem da câmera de segurança para identificar horários e pessoas"
    },
    {
      "id": "HANDWRITING-EVD004",
      "evidenceId": "EVD004",
      "analysisType": "HandwritingAnalysis",
      "responseTime": 75,
      "resultFile": "forensics/analise_caligrafia.pdf",
      "description": "Comparação da caligrafia da carta com amostras dos suspeitos"
    }
  ],
  "temporalEvents": [
    {
      "id": "MEMO001",
      "triggerTime": 30,
      "type": "memo",
      "title": "Orientação para Caso Tutorial",
      "content": "Este é um caso tutorial. Foque nas evidências principais: fio de cabelo, câmera de segurança e carta manuscrita. As análises forenses serão essenciais para resolver o caso.",
      "fileName": "memos/memo_tutorial.txt"
    },
    {
      "id": "WITNESS001",
      "triggerTime": 45,
      "type": "witness",
      "title": "Depoimento do Segurança",
      "content": "Segurança noturno se lembra de ter visto uma mulher loira saindo pela porta dos fundos por volta das 03:45. Ela parecia conhecer o código da porta de emergência.",
      "fileName": "witnesses/seguranca_statement.pdf"
    },
    {
      "id": "MEMO002",
      "triggerTime": 60,
      "type": "memo",
      "title": "Atualização do Laboratório",
      "content": "Análises de DNA estão sendo processadas. Lembre-se de que dois suspeitos têm cabelo loiro - será necessário DNA para diferenciar.",
      "fileName": "memos/memo_dna.txt"
    }
  ],
  "timeline": [
    {
      "time": "2024-02-04T22:00:00Z",
      "event": "Joana Duarte registra saída da clínica (horário oficial)",
      "source": "Sistema de ponto eletrônico"
    },
    {
      "time": "2024-02-05T00:00:00Z",
      "event": "Roberto Silva termina plantão no hospital público",
      "source": "Livro de ponto do hospital"
    },
    {
      "time": "2024-02-05T01:00:00Z",
      "event": "Roberto Silva chega em casa (confirmado por família)",
      "source": "Depoimento dos familiares"
    },
    {
      "time": "2024-02-05T03:30:00Z",
      "event": "Horário estimado do roubo",
      "source": "Análise da cena e sistema de alarme"
    },
    {
      "time": "2024-02-05T03:45:00Z",
      "event": "Mulher loira vista saindo pela porta dos fundos",
      "source": "Depoimento do segurança"
    },
    {
      "time": "2024-02-05T07:30:00Z",
      "event": "Descoberta do roubo pela primeira funcionária a chegar",
      "source": "Chamada para a polícia"
    }
  ],
  "solution": {
    "culprit": "Joana Duarte",
    "keyEvidence": "EVD002",
    "explanation": "Joana Duarte é a culpada. O DNA do fio de cabelo loiro encontrado na cena corresponde ao dela. Embora Roberto Silva também tenha cabelo loiro, seu álibi é verificável. A câmera de segurança mostra que o sistema foi desativado às 22:30 (quando Joana ainda estava na clínica), contradizendo seu álibi. A carta manuscrita revela chantagem relacionada aos medicamentos controlados. Joana tinha acesso, motivo (problemas financeiros) e oportunidade.",
    "requiredEvidence": ["EVD002", "DNA-EVD002"],
    "minimumScore": 70
  },
  "unlockLogic": {
    "progressionRules": [
      {
        "condition": "evidenceExamined",
        "target": "EVD001",
        "unlocks": ["EVD004", "SUS003"],
        "delay": 15
      },
      {
        "condition": "evidenceExamined",
        "target": "EVD002",
        "unlocks": ["EVD005"],
        "delay": 10
      },
      {
        "condition": "evidenceExamined",
        "target": "EVD003",
        "unlocks": ["EVD006"],
        "delay": 5
      },
      {
        "condition": "evidenceExamined",
        "target": "EVD004",
        "unlocks": ["EVD007"],
        "delay": 8
      },
      {
        "condition": "evidenceExamined",
        "target": "EVD005",
        "unlocks": ["EVD008"],
        "delay": 12
      },
      {
        "condition": "evidenceExamined",
        "target": "EVD006",
        "unlocks": ["EVD009"],
        "delay": 7
      },
      {
        "condition": "evidenceExamined",
        "target": "EVD007",
        "unlocks": ["EVD010"],
        "delay": 15
      }
    ],
    "analysisRules": [
      {
        "evidenceId": "EVD002",
        "analysisType": "DNA",
        "unlocks": ["solution.keyEvidence"],
        "critical": true
      },
      {
        "evidenceId": "EVD003",
        "analysisType": "DigitalForensics",
        "unlocks": ["solution.support"],
        "critical": true
      },
      {
        "evidenceId": "EVD004",
        "analysisType": "HandwritingAnalysis",
        "unlocks": ["solution.motive"],
        "critical": false
      }
    ]
  },
  "gameMetadata": {
    "version": "1.0",
    "createdBy": "Sistema CaseZero - Tutorial",
    "createdAt": "2024-02-05T08:00:00Z",
    "tags": ["roubo", "clinica", "tutorial", "cabelo_loiro", "dna"],
    "difficulty": "beginner",
    "estimatedPlayTime": "60-120 minutes"
  }
}